<?xml version="1.0" encoding="UTF-8"?><record_update table="sys_ux_client_script">
    <sys_ux_client_script action="DELETE">
        <controller_preset/>
        <includes/>
        <macroponent display_value="360 CI Dashboard v2 default copy">95e0db5197c40ed0917df9f0f053afa4</macroponent>
        <name>filter_14/datasource</name>
        <preset/>
        <required_translations>[
    
]</required_translations>
        <script><![CDATA[/**
 * @param {params} params
 * @param {api} params.api
 * @param {TransformApiHelpers} params.helpers
 */
function evaluateProperty({
    api,
    helpers
}) {
    return {
        "encodedQuery": "name=cmdb_ci_win_server",
        "table": {
            "id": "sys_metric",
            "label": "Time Series Metrics"
        },
        "type": "table"
    };
}]]></script>
        <script_api_version>2.0.0</script_api_version>
        <sys_class_name>sys_ux_client_script</sys_class_name>
        <sys_created_by>optimiz</sys_created_by>
        <sys_created_on>2024-01-29 16:52:47</sys_created_on>
        <sys_id>75e0939197c40ed0917df9f0f053af24</sys_id>
        <sys_mod_count>1</sys_mod_count>
        <sys_name>filter_14/datasource</sys_name>
        <sys_package display_value="Optimiz AIOps Insights" source="x_opti8_optimiz_ai">d4d83ad9878802d0e7ae55b83cbb3590</sys_package>
        <sys_policy/>
        <sys_scope display_value="Optimiz AIOps Insights">d4d83ad9878802d0e7ae55b83cbb3590</sys_scope>
        <sys_update_name>sys_ux_client_script_75e0939197c40ed0917df9f0f053af24</sys_update_name>
        <sys_updated_by>optimiz</sys_updated_by>
        <sys_updated_on>2024-01-29 16:52:47</sys_updated_on>
        <target>macroponent</target>
        <type>transform</type>
    </sys_ux_client_script>
    <sys_update_version action="INSERT_OR_UPDATE">
        <action>DELETE</action>
        <application display_value="Optimiz AIOps Insights">d4d83ad9878802d0e7ae55b83cbb3590</application>
        <file_path/>
        <instance_id>81ea05e71b2a79541024eb9b2d4bcbca</instance_id>
        <instance_name>aiops12</instance_name>
        <name>sys_ux_client_script_75e0939197c40ed0917df9f0f053af24</name>
        <payload>&lt;?xml version="1.0" encoding="UTF-8"?&gt;&lt;record_update table="sys_ux_client_script"&gt;&lt;sys_ux_client_script action="INSERT_OR_UPDATE"&gt;&lt;controller_preset/&gt;&lt;includes/&gt;&lt;macroponent display_value="360 CI Dashboard v2 default copy"&gt;95e0db5197c40ed0917df9f0f053afa4&lt;/macroponent&gt;&lt;name&gt;filter_14/datasource&lt;/name&gt;&lt;preset/&gt;&lt;required_translations&gt;[
    
]&lt;/required_translations&gt;&lt;script&gt;&lt;![CDATA[/**
 * @param {params} params
 * @param {api} params.api
 * @param {TransformApiHelpers} params.helpers
 */
function evaluateProperty({
    api,
    helpers
}) {
    return {
        "encodedQuery": "name=cmdb_ci_win_server",
        "table": {
            "id": "sys_metric",
            "label": "Time Series Metrics"
        },
        "type": "table"
    };
}]]&gt;&lt;/script&gt;&lt;script_api_version&gt;2.0.0&lt;/script_api_version&gt;&lt;sys_class_name&gt;sys_ux_client_script&lt;/sys_class_name&gt;&lt;sys_created_by&gt;optimiz&lt;/sys_created_by&gt;&lt;sys_created_on&gt;2024-01-29 16:52:47&lt;/sys_created_on&gt;&lt;sys_id&gt;75e0939197c40ed0917df9f0f053af24&lt;/sys_id&gt;&lt;sys_mod_count&gt;1&lt;/sys_mod_count&gt;&lt;sys_name&gt;filter_14/datasource&lt;/sys_name&gt;&lt;sys_package display_value="Optimiz AIOps Insights" source="x_opti8_optimiz_ai"&gt;d4d83ad9878802d0e7ae55b83cbb3590&lt;/sys_package&gt;&lt;sys_policy/&gt;&lt;sys_scope display_value="Optimiz AIOps Insights"&gt;d4d83ad9878802d0e7ae55b83cbb3590&lt;/sys_scope&gt;&lt;sys_update_name&gt;sys_ux_client_script_75e0939197c40ed0917df9f0f053af24&lt;/sys_update_name&gt;&lt;sys_updated_by&gt;optimiz&lt;/sys_updated_by&gt;&lt;sys_updated_on&gt;2024-01-29 16:52:47&lt;/sys_updated_on&gt;&lt;target&gt;macroponent&lt;/target&gt;&lt;type&gt;transform&lt;/type&gt;&lt;/sys_ux_client_script&gt;&lt;/record_update&gt;</payload>
        <payload_hash>786107408</payload_hash>
        <record_name>filter_14/datasource</record_name>
        <reverted_from/>
        <source>5e2af6d197040ed0917df9f0f053afdb</source>
        <source_table>sys_update_set</source_table>
        <state>previous</state>
        <sys_created_by>optimiz</sys_created_by>
        <sys_created_on>2024-01-29 16:52:54</sys_created_on>
        <sys_id>5fe0131147084a50118c2d8fe16d43fa</sys_id>
        <sys_mod_count>0</sys_mod_count>
        <sys_recorded_at>18d56235d290000001</sys_recorded_at>
        <sys_updated_by>optimiz</sys_updated_by>
        <sys_updated_on>2024-01-29 16:52:54</sys_updated_on>
        <type>UX Client Script</type>
        <update_guid>93e0131170084a50911b00fcea7c66fa</update_guid>
        <update_guid_history>93e0131170084a50911b00fcea7c66fa:786107408,bde0939126c40ed064bddd2148f39a25:-533971461</update_guid_history>
    </sys_update_version>
    <sys_metadata_delete action="INSERT_OR_UPDATE">
        <sys_audit_delete/>
        <sys_class_name>sys_metadata_delete</sys_class_name>
        <sys_created_by>optimiz</sys_created_by>
        <sys_created_on>2024-01-29 17:42:14</sys_created_on>
        <sys_db_object display_value="" name="sys_ux_client_script">sys_ux_client_script</sys_db_object>
        <sys_id>6819803a1af34424824c14f560f9e210</sys_id>
        <sys_metadata>75e0939197c40ed0917df9f0f053af24</sys_metadata>
        <sys_mod_count>0</sys_mod_count>
        <sys_name>filter_14/datasource</sys_name>
        <sys_package display_value="Optimiz AIOps Insights" source="x_opti8_optimiz_ai">d4d83ad9878802d0e7ae55b83cbb3590</sys_package>
        <sys_parent/>
        <sys_policy/>
        <sys_scope display_value="Optimiz AIOps Insights">d4d83ad9878802d0e7ae55b83cbb3590</sys_scope>
        <sys_scope_delete display_value="">061108c75cdc4410a9ad203e0b8d2900</sys_scope_delete>
        <sys_update_name>sys_ux_client_script_75e0939197c40ed0917df9f0f053af24</sys_update_name>
        <sys_update_version display_value="sys_ux_client_script_75e0939197c40ed0917df9f0f053af24">5fe0131147084a50118c2d8fe16d43fa</sys_update_version>
        <sys_updated_by>optimiz</sys_updated_by>
        <sys_updated_on>2024-01-29 17:42:14</sys_updated_on>
    </sys_metadata_delete>
</record_update>
